{
  "name": "Warren Sparks",
  "age": 28,
  "address": {
    "street": "Nawcuz Plaza",
    "city": "Akacetzib",
    "state": "MT",
    "zip": "86278"
  },
  "contact": {
    "phone": "(582) 988-9718",
    "servicePhone": "800472617"
  },
  "birthday": "1966-09-04T15:11:45.873Z",
  "ip": "79.7.92.12",
  "foo": "bar",
  "profile": {
    "about": "Rihewi ovodawe racfit gabe bol ti zeumenu sow ta mosve ler le witet. Kis vu siidu zusac pihduwa cajat ju pe gosrujbe giv macledvi jeka gin boc dekofos tuzus nefruugu. Mez jerzeco se suorazu ludepu vigo tu fafvifji ecija deilisog gewinadi moj ufo.",
    "bio": "Baw howciguz fona imize zasad ivoh demodsec mairecob baneer bava seebojid le rusedmih egovuw boj. Cufeod ohegazag du sowdafow radcofa iwnal irgi uj pahjoir babzapu nutej ab. Loseafi gewri wir garva paumjor vocpes jocze fa wirjinal lamuduha sapuf redaweh ic hujuvlo voz fi puwito opipok. Akuvajub gu tobab or luh zeiz cabubhef ajo wujijes pubi zumuw oriina je buhte mo dij. Sa pupeg vavasas vopji owu mom hovolu wis julda ogbip fugudazu gub ta. Jais lacmef ihe law avvog dovocle rocho toikzan co lorup cudoah ihoem messohib wizfiik tedgal jur tapuv putiglap."
  },
  "apiKey": "f9ae492245ab842caf84b858eea97f6a49ae068888b0bdf4002b4becaababe69",
  "currency": {
    "code": "BND",
    "name": "Brunei Darussalam Dollar"
  }
}