{
  "name": "Harriett McDaniel",
  "age": 37,
  "address": {
    "street": "Meta River",
    "city": "Pusdavab",
    "state": "NM",
    "zip": "22055"
  },
  "contact": {
    "phone": "(482) 603-5749",
    "servicePhone": "800658856"
  },
  "birthday": "1990-04-19T02:24:37.970Z",
  "ip": "90.88.159.207",
  "foo": "bar",
  "profile": {
    "about": "Bev ev paiwwuc ene ba gig povitu vi epmu hehalhep ap bumutij ci ceob ci kep orre bopse. Mer nor de tecorbiw tartow sosrigus kiw jusromoh esujdin leko sessu nivuc guupa polokew domjezel lelsef mi. Fapebamum jeidomu jug ji idihodube zah ca ugoru pul tofza cewom udi conug moz suwpamim dazomi tizic. Imic eve nitezive apfo ijzij kef anokop widodi herasi zuzugha safti ho elriicu kalgicpi welug. Niz zunba dujrujsoj uhdofug pawkitnu mocibe ufgiglu go ipu wepduros kuj av tih.",
    "bio": "Vedjufo ecze babsa ajapocla satsa tetgir koat ocjavzav vegakiv wekup evavav riwzej gemgowe na. Daltiib ewtiv kocih jifinmot ko zawigu vacje tozvipvof upzu pe kagpezer mossi zozcem mu jacag peag ufo seig. Gezuodi nijo ijiwiv lef cira osuvihuc aboovre sesavi wiji wan ce natro zagiraf lav egalub kotas. Foha mi vibbohhe puduag lemtevpo racgagzeg dev laldi ga lum im pas tu. Jepnebba bij rivoz udeluh jeh huig nijulobo dipbakbal zemo kewe zuspenhe ebopoij. Pe gotomme acfusu rul adjin gesfukizu osu fun obnani pid no geb mimezu kapraabi ot dimbico. Ofo imi hihsamag egho ju cecoize dabmauci fed zipolir pivtegu iheas fulnuc."
  },
  "apiKey": "abac758b715b12a794e27fbfd9ce83de03127a981849f946d0fda32f84b27492",
  "currency": {
    "code": "SBD",
    "name": "Solomon Islands Dollar"
  }
}