{
  "name": "Lydia Love",
  "age": 25,
  "address": {
    "street": "Pebe Path",
    "city": "Udocukko",
    "state": "OK",
    "zip": "38179"
  },
  "contact": {
    "phone": "(282) 665-8030",
    "servicePhone": "800829688"
  },
  "birthday": "1971-12-11T15:11:07.385Z",
  "ip": "150.105.28.242",
  "foo": "bar",
  "profile": {
    "about": "Of osdioc bepedvun kel comavob pelhavkuz jalara gimad dimzud ku oveje obcemup sescacom. Ino cerepo ewudezir hib za toleznoz ditah dorfo zer wohoziog somekmuz ehisi mohnubic ba hoekkud fu. Abavic ejsi dur ja fo hizag zeap sehsip urzevep abug geuhma mawomun fuvaf roiz gil hij. Sapge guf udmuwij guhomele comtokabu debo uh liijoaj tegre le pin ic. Vitelom wem ezlamiji takeeg jatavi nahve sedvaror butduvo ibi bubfuj curkagut zapipne nebcoir ag ube gokug.",
    "bio": "Inamiwa iz totohok teperasu waluweohi uberrud roz uda ri mer vofe witasjaw tu. Eho ku fu iraiba ja loruuke pindaufe ha nozzu tukcij kuc tibahu jic kaho vuh wu vec roj. At gihbu elvazowu sawic sig epucodho jatazeb hadohcin lij apu wizik ik vulizcor nepupiet vucigip vawakuh ziz johon. Ruadgof nobuzos izpu rurus lencibug dihzatuk rer piveggob ibuhes beva zakrop howcoto pi nonug beniru eguobes budbiji. Vugfugol ju se hokivi amiesemi ec os ne ate hef todo ubbub."
  },
  "apiKey": "2b27bad858b738bf341c097e2e34985d930b19a9c67cad2f1122705e2853086e",
  "currency": {
    "code": "XCD",
    "name": "East Caribbean Dollar"
  }
}