{
  "name": "Bettie Clarke",
  "age": 36,
  "address": {
    "street": "Nilci Parkway",
    "city": "Puzvucag",
    "state": "DC",
    "zip": "24827"
  },
  "contact": {
    "phone": "(483) 434-4238",
    "servicePhone": "800626132"
  },
  "birthday": "1971-02-04T07:47:44.059Z",
  "ip": "236.121.176.181",
  "foo": "bar",
  "profile": {
    "about": "Li adpaca tosudag uvduok kola oz aze ewazuwuf zoceb zirwefmuw zup cal bimlembe fuaru moozabup hugwarij nuda vuwo. Ure giicuzon dubufmic vaguf ba ilusek ibiuhuco daum iloci kerred cec aspomma se gufel elonit tipez tusgocec. Deewicab pulmomuz winav ruwib nip mimi ganipi co wu lumsuv zozrut at tufjis. Ufvac uwuzo tovakin ibopezaz mezo cojeh um ebu vetoim vubgod kaho eb mocucat lu. Hoej gapne nerro zon cocrim wojwalri nofifu so bib nosla omso ogeconowe uzeni higpekim olu hejge duvbus. Sur cufito jupu uz vemmu wieg zalato we laga fufnu fow zozojfib gak.",
    "bio": "Vifjirter lo abto dehab wi mukuhij owdollih licu kazeub rep ule unpu guog jalcofime onicejmi zuto. Cug ipo dojfejjub memeloj vu savab if vobcoc gow ki koeko fo akewu bilnulef uwbifpap wudet. Bivo ihoki alo za oro icisadab bu wemij ut jun va wupife wopcac wulok ada so tehvif. Jutha iko mimomna piho li vew agfi bopu mir dowiwukum bovdot wa wewuf vobtowuv higtusaw gatcok fekisko tin. Wuse fisi hav jojgogse hutij jaz lahoza asuzja ba kic rafpaz behfi vet lekmeciwu otca zuvogeta ka do. Tehlu ari zu fi tumsa igokocib fab ri nizogezan ofu jeh ijwur na. Ta ivo kunec lowovhu fu ki rajepke el pedle rulhedhi bo utoig etlu sulfik motap."
  },
  "apiKey": "5e82025165fc2445d559e66fd808ede93cf249bea7a2fe6589414058bd13ee99",
  "currency": {
    "code": "XPF",
    "name": "Comptoirs Français du Pacifique (CFP) Franc"
  }
}